zipfile_deflate64/__init__.py
zipfile_deflate64/_patcher.py
zipfile_deflate64/_zipfile.py
zipfile_deflate64/deflate64.cp39-win_amd64.pyd
zipfile_deflate64-0.1.6.dist-info/LICENSE
zipfile_deflate64-0.1.6.dist-info/METADATA
zipfile_deflate64-0.1.6.dist-info/WHEEL
zipfile_deflate64-0.1.6.dist-info/top_level.txt
zipfile_deflate64-0.1.6.dist-info/RECORD
