Metadata-Version: 2.1
Name: zipfile-deflate64
Version: 0.1.6
Summary: Extract Deflate64 ZIP archives with Python's zipfile API.
Home-page: https://github.com/brianhelba/zipfile-deflate64
Author: Kitware, Inc.
Author-email: kitware@kitware.com
License: Apache 2.0
Project-URL: Bug Reports, https://github.com/brianhelba/zipfile-deflate64/issues
Project-URL: Source, https://github.com/brianhelba/zipfile-deflate64
Keywords: zip zipfile deflate deflate64
Platform: UNKNOWN
Classifier: Development Status :: 3 - Alpha
Classifier: Intended Audience :: Developers
Classifier: License :: OSI Approved :: Apache Software License
Classifier: Operating System :: MacOS :: MacOS X
Classifier: Operating System :: Microsoft :: Windows
Classifier: Operating System :: POSIX :: Linux
Classifier: Programming Language :: Python :: 3
Classifier: Programming Language :: Python :: 3.6
Classifier: Programming Language :: Python :: 3.7
Classifier: Programming Language :: Python :: 3.8
Classifier: Programming Language :: Python :: 3.9
Classifier: Programming Language :: Python
Classifier: Topic :: System :: Archiving
Classifier: Topic :: System :: Archiving :: Compression
Requires-Python: >=3.6
